didit
