Metadata-Version: 1.0
Name: didit
Version: 0.2.0dev
Summary: Lightweight, commandline tool to remember what I did last week
Home-page: http://github.com/ralphbean/didit
Author: Ralph Bean
Author-email: ralph.bean@gmail.com
License: GPLv3+
Platform: UNKNOWN
Classifier: Development Status :: 5 - Production/Stable
Classifier: Environment :: Console
Classifier: Intended Audience :: Developers
Classifier: Intended Audience :: End Users/Desktop
Classifier: Intended Audience :: System Administrators
Classifier: License :: OSI Approved :: GNU General Public License (GPL)
Classifier: Natural Language :: English
Classifier: Topic :: Office/Business :: News/Diary
Classifier: Topic :: Text Processing :: Markup
Classifier: Topic :: Utilities
